attention_paper/__init__.py
attention_paper/open_paper.py
attention_paper/data/attentionalluneed.pdf
attention_paper-0.1.1.dist-info/METADATA
attention_paper-0.1.1.dist-info/WHEEL
attention_paper-0.1.1.dist-info/entry_points.txt
attention_paper-0.1.1.dist-info/top_level.txt
attention_paper-0.1.1.dist-info/RECORD
