Metadata-Version: 2.2
Name: attention_paper
Version: 0.1.1
Summary: Easily open the 'Attention Is All You Need' paper
Home-page: https://github.com/Rktim/attention
Author: Raktim Kalita
Author-email: raktmxx@gmail.com
Classifier: Programming Language :: Python :: 3
Classifier: License :: OSI Approved :: MIT License
Classifier: Operating System :: OS Independent
Requires-Python: >=3.6
Dynamic: author
Dynamic: author-email
Dynamic: classifier
Dynamic: home-page
Dynamic: requires-python
Dynamic: summary
